ripandtear/__init__.py
ripandtear/__main__.py
ripandtear/extractors/__init__.py
ripandtear/extractors/bunkr.py
ripandtear/extractors/common.py
ripandtear/extractors/coomer.py
ripandtear/extractors/cyberdrop.py
ripandtear/extractors/gfycat.py
ripandtear/extractors/gofile.py
ripandtear/extractors/imgur.py
ripandtear/extractors/jpg.py
ripandtear/extractors/reddit.py
ripandtear/extractors/redgifs.py
ripandtear/extractors/tiktits.py
ripandtear/utils/__init__.py
ripandtear/utils/cli_arguments.py
ripandtear/utils/color.py
ripandtear/utils/conductor.py
ripandtear/utils/content_finder.py
ripandtear/utils/custom_types.py
ripandtear/utils/downloader.py
ripandtear/utils/file_extension_corrector.py
ripandtear/utils/file_hasher.py
ripandtear/utils/file_sorter.py
ripandtear/utils/logger.py
ripandtear/utils/progress.py
ripandtear/utils/rat_info.py
ripandtear/utils/tracker.py
ripandtear-0.9.45.dist-info/LICENSE
ripandtear-0.9.45.dist-info/METADATA
ripandtear-0.9.45.dist-info/WHEEL
ripandtear-0.9.45.dist-info/entry_points.txt
ripandtear-0.9.45.dist-info/top_level.txt
ripandtear-0.9.45.dist-info/RECORD
