Metadata-Version: 2.1
Name: ripandtear
Version: 0.9.45
Summary: An asynchronous file archival program
Home-page: https://gitlab.com/johnny_barracuda/ripandtear/
Author: Johnny-Barracuda
Author-email: johnny_barracuda@protonmail.ch
Project-URL: Bug Tracker, https://gitlab.com/johnny_barracuda/ripandtear/
Requires-Python: >=3.10
License-File: LICENSE
Requires-Dist: aiofiles ==22.1.0
Requires-Dist: anyio ==3.6.2
Requires-Dist: asyncio ==3.4.3
Requires-Dist: beautifulsoup4 ==4.11.1
Requires-Dist: Brotli ==1.0.9
Requires-Dist: certifi ==2022.9.24
Requires-Dist: charset-normalizer ==2.1.1
Requires-Dist: greenlet ==1.1.3
Requires-Dist: h11 ==0.14.0
Requires-Dist: httpcore ==0.16.3
Requires-Dist: httpx ==0.23.3
Requires-Dist: idna ==3.4
Requires-Dist: mutagen ==1.46.0
Requires-Dist: playwright ==1.26.0
Requires-Dist: pycryptodomex ==3.17
Requires-Dist: pyee ==8.1.0
Requires-Dist: python-magic ==0.4.27
Requires-Dist: rfc3986 ==1.5.0
Requires-Dist: rich ==13.3.1
Requires-Dist: sniffio ==1.3.0
Requires-Dist: soupsieve ==2.3.2.post1
Requires-Dist: typing-extensions ==4.4.0
Requires-Dist: urllib3 ==1.26.12
Requires-Dist: websockets ==10.1
Requires-Dist: yt-dlp ==2023.10.13
